excsv/__init__.py
excsv/cli.py
excsv/utils/__init__.py
excsv/utils/excel.py
excsv/utils/infer.py
excsv/utils/listing.py
excsv/utils/text.py
excsv-0.1.4.1.dist-info/METADATA
excsv-0.1.4.1.dist-info/WHEEL
excsv-0.1.4.1.dist-info/entry_points.txt
excsv-0.1.4.1.dist-info/top_level.txt
excsv-0.1.4.1.dist-info/RECORD
