Metadata-Version: 2.1
Name: excsv
Version: 0.1.4.1
Summary: A command-line utility for converting CSV files into Excel sheets.
Home-page: https://github.com/dannguyen/excsv
Author: Dan Nguyen
License: Apache License, Version 2.0
Project-URL: Issues, https://github.dannguyen/dannguyen/excsv/issues
Project-URL: CI, https://github.com/dannguyen/excsv/actions
Project-URL: Changelog, https://github.com/dannguyen/excsv/releases
Requires-Python: >=3.8
Requires-Dist: click >=8.1
Requires-Dist: hyperloglog
Requires-Dist: rich-click
Requires-Dist: openpyxl
Requires-Dist: click-default-group >=1.2.3
Requires-Dist: setuptools
Requires-Dist: pip
Requires-Dist: pyreadline3 ; sys_platform == "win32"
Provides-Extra: test
Requires-Dist: pytest ; extra == 'test'
Requires-Dist: pytest-mock ; extra == 'test'
Requires-Dist: black >=24.2.0 ; extra == 'test'
Requires-Dist: types-click ; extra == 'test'
